pylabelbuddy/__init__.py
pylabelbuddy/_annotations_manager.py
pylabelbuddy/_annotations_navigator.py
pylabelbuddy/_annotations_notebook.py
pylabelbuddy/_annotator.py
pylabelbuddy/_database.py
pylabelbuddy/_dataset_manager.py
pylabelbuddy/_dataset_menu.py
pylabelbuddy/_import_export_menu.py
pylabelbuddy/_label_buddy.py
pylabelbuddy/_scrollable_frame.py
pylabelbuddy/_scrollable_list.py
pylabelbuddy/_searchable_text.py
pylabelbuddy/_utils.py
pylabelbuddy/_data/PLB.png
pylabelbuddy/_data/VERSION.txt
pylabelbuddy/_data/__init__.py
pylabelbuddy/_data/create_database.sql
pylabelbuddy-0.1.4.dist-info/LICENSE
pylabelbuddy-0.1.4.dist-info/METADATA
pylabelbuddy-0.1.4.dist-info/WHEEL
pylabelbuddy-0.1.4.dist-info/entry_points.txt
pylabelbuddy-0.1.4.dist-info/top_level.txt
pylabelbuddy-0.1.4.dist-info/RECORD
