Metadata-Version: 2.1
Name: pylabelbuddy
Version: 0.1.4
Summary: DEPRECATED. A small application for annotating text
Home-page: https://github.com/jeromedockes/pylabelbuddy
Maintainer: Jerome Dockes
Maintainer-email: jerome@dockes.org
License: BSD 3-Clause License
Platform: UNKNOWN
Classifier: Programming Language :: Python :: 3
Requires-Python: >=3.6
